recorder_viz/__init__.py
recorder_viz/build_offset_intervals.py
recorder_viz/creader_wrapper.py
recorder_viz/html_writer.py
recorder_viz/librreader.so
recorder_viz/reporter.py
recorder_viz-0.0.4.dist-info/LICENSE
recorder_viz-0.0.4.dist-info/METADATA
recorder_viz-0.0.4.dist-info/WHEEL
recorder_viz-0.0.4.dist-info/top_level.txt
recorder_viz-0.0.4.dist-info/RECORD
